images_to_pdf/__init__.py
images_to_pdf/cli.py
images_to_pdf/images_to_pdf.py
images_to_pdf-0.1.0.dist-info/AUTHORS.rst
images_to_pdf-0.1.0.dist-info/LICENSE
images_to_pdf-0.1.0.dist-info/METADATA
images_to_pdf-0.1.0.dist-info/WHEEL
images_to_pdf-0.1.0.dist-info/entry_points.txt
images_to_pdf-0.1.0.dist-info/top_level.txt
images_to_pdf-0.1.0.dist-info/RECORD
