Metadata-Version: 2.1
Name: images-to-pdf
Version: 0.1.0
Summary: Convert all passed images into a single pdf file
Home-page: https://github.com/lucas8107/images-to-pdf
Author: Lucas Paula
Author-email: luolcami@gmail.com
License: MIT license
Keywords: images_to_pdf
Platform: UNKNOWN
Classifier: Development Status :: 2 - Pre-Alpha
Classifier: Intended Audience :: Developers
Classifier: License :: OSI Approved :: MIT License
Classifier: Natural Language :: English
Classifier: Programming Language :: Python :: 3
Classifier: Programming Language :: Python :: 3.6
Classifier: Programming Language :: Python :: 3.7
Classifier: Programming Language :: Python :: 3.8
Requires-Python: >=3.6
Requires-Dist: Click (>=7.0)
Requires-Dist: Pillow (==9.1.0)
